svglang/__init__.py
svglang/cli/__init__.py
svglang/cli/main.py
svglang/core/__init__.py
svglang/core/ast.py
svglang/execution/__init__.py
svglang/execution/interpreter.py
svglang/parsing/__init__.py
svglang/parsing/parser.py
svglang/parsing/transformer.py
svglang/parsing/transformer_backup.py
svglang/parsing/transformer_new.py
svglang/parsing/grammar/__init__.py
svglang/parsing/grammar/base.py
svglang/parsing/grammar/expressions.py
svglang/parsing/grammar/shapes.py
svglang/parsing/grammar/statements.py
svglang/parsing/transformers/__init__.py
svglang/parsing/transformers/base_transformer.py
svglang/parsing/transformers/expression_transformer.py
svglang/parsing/transformers/statement_transformer.py
svglang_core-0.1.0.dist-info/licenses/LICENSE
svglang_core-0.1.0.dist-info/METADATA
svglang_core-0.1.0.dist-info/WHEEL
svglang_core-0.1.0.dist-info/entry_points.txt
svglang_core-0.1.0.dist-info/top_level.txt
svglang_core-0.1.0.dist-info/RECORD
