Metadata-Version: 2.4
Name: svglang-core
Version: 0.1.0
Summary: SVG Domain Specific Language Compiler - Core Engine
Author-email: Florian Scholz <scholzf@uni-bremen.de>
License: MIT
Project-URL: Homepage, https://github.com/SVGLang/svglang
Project-URL: Repository, https://github.com/SVGLang/svglang
Project-URL: Documentation, https://github.com/SVGLang/svglang#readme
Project-URL: Issues, https://github.com/SVGLang/svglang/issues
Keywords: svg,dsl,compiler,graphics
Classifier: Development Status :: 4 - Beta
Classifier: Intended Audience :: Developers
Classifier: License :: OSI Approved :: MIT License
Classifier: Programming Language :: Python :: 3
Classifier: Programming Language :: Python :: 3.8
Classifier: Programming Language :: Python :: 3.9
Classifier: Programming Language :: Python :: 3.10
Classifier: Programming Language :: Python :: 3.11
Classifier: Programming Language :: Python :: 3.12
Classifier: Topic :: Software Development :: Compilers
Requires-Python: >=3.8
License-File: LICENSE
Requires-Dist: lark>=1.1.0
Dynamic: license-file
